demiansoft_extras/__init__.py
demiansoft_extras/db.sqlite3
demiansoft_extras/manage.py
demiansoft_extras/_data/analyticsds.py
demiansoft_extras/analyticsds/__init__.py
demiansoft_extras/analyticsds/admin.py
demiansoft_extras/analyticsds/apps.py
demiansoft_extras/analyticsds/models.py
demiansoft_extras/analyticsds/migrations/__init__.py
demiansoft_extras/analyticsds/templates/analyticsds.html
demiansoft_extras/analyticsds/templatetags/__init__.py
demiansoft_extras/analyticsds/templatetags/analyticsds_tags.py
demiansoft_extras/calendards/__init__.py
demiansoft_extras/calendards/admin.py
demiansoft_extras/calendards/apps.py
demiansoft_extras/calendards/models.py
demiansoft_extras/calendards/migrations/0001_initial.py
demiansoft_extras/calendards/migrations/0002_event_delete_caldate.py
demiansoft_extras/calendards/migrations/__init__.py
demiansoft_extras/calendards/static/calendards/fullcalendar4/packages/bootstrap/LICENSE.txt
demiansoft_extras/calendards/static/calendards/fullcalendar4/packages/bootstrap/README.md
demiansoft_extras/calendards/static/calendards/fullcalendar4/packages/bootstrap/main.css
demiansoft_extras/calendards/static/calendards/fullcalendar4/packages/bootstrap/main.d.ts
demiansoft_extras/calendards/static/calendards/fullcalendar4/packages/bootstrap/main.esm.js
demiansoft_extras/calendards/static/calendards/fullcalendar4/packages/bootstrap/main.js
demiansoft_extras/calendards/static/calendards/fullcalendar4/packages/bootstrap/main.min.css
demiansoft_extras/calendards/static/calendards/fullcalendar4/packages/bootstrap/main.min.js
demiansoft_extras/calendards/static/calendards/fullcalendar4/packages/bootstrap/package.json
demiansoft_extras/calendards/static/calendards/fullcalendar4/packages/core/LICENSE.txt
demiansoft_extras/calendards/static/calendards/fullcalendar4/packages/core/README.md
demiansoft_extras/calendards/static/calendards/fullcalendar4/packages/core/locales-all.js
demiansoft_extras-0.1.0.dist-info/LICENSE
demiansoft_extras-0.1.0.dist-info/WHEEL
demiansoft_extras-0.1.0.dist-info/METADATA
demiansoft_extras-0.1.0.dist-info/RECORD
