Metadata-Version: 2.1
Name: demiansoft_extras
Version: 0.1.0
Summary: my demiansoft_extras
Author-email: Hyungjin Kim <hj3415@gmail.com>
Classifier: License :: OSI Approved :: MIT License
Project-URL: Home, https://www.demiansoft.com
